{
   "_command": {
      "addr": "8",
      "delay": 150,
      "first_char": "&",
      "n_mex": 2520,
      "relay": 2
   },
   "1": {
      "_info": {
         "end_sent": "2019-12-27 18:34:59.764145",
         "end_test": "2019-12-27 18:35:13.115114",
         "start": "2019-12-27 18:28:41.957913",
         "time_send": "0:6.17 [h:m.s]",
         "time_test": "0:6.31 [h:m.s]"
      },
      "mex_": {
         "S": 2520,
         "R": 2031,
         "L": 489,
         "E": 0
      },
      "statistic_": {
         "sample_size": 2031,
         "pdr": 0.805952380952381,
         "goodput": 10.384571700624273,
         "latency": {
            "mean": 9.301247522402758,
            "std": 2.668216310123867,
            "m_e": 0.11604385406648174,
            "low": 9.185203668336277,
            "up": 9.417291376469239
         }
      }
   },
   "2": {
      "_info": {
         "end_sent": "2019-12-27 18:43:13.740149",
         "end_test": "2019-12-27 18:43:27.202929",
         "start": "2019-12-27 18:36:55.905601",
         "time_send": "0:6.17 [h:m.s]",
         "time_test": "0:6.31 [h:m.s]"
      },
      "mex_": {
         "S": 2520,
         "R": 2006,
         "L": 514,
         "E": 0
      },
      "statistic_": {
         "sample_size": 2006,
         "pdr": 0.796031746031746,
         "goodput": 10.253072824458439,
         "latency": {
            "mean": 9.332529226819542,
            "std": 2.5706520236674595,
            "m_e": 0.11249517596343701,
            "low": 9.220034050856105,
            "up": 9.445024402782979
         }
      }
   },
   "3": {
      "_info": {
         "end_sent": "2019-12-27 18:50:45.603743",
         "end_test": "2019-12-27 18:50:58.603252",
         "start": "2019-12-27 18:44:27.759706",
         "time_send": "0:6.17 [h:m.s]",
         "time_test": "0:6.30 [h:m.s]"
      },
      "mex_": {
         "S": 2520,
         "R": 2013,
         "L": 507,
         "E": 0
      },
      "statistic_": {
         "sample_size": 2013,
         "pdr": 0.7988095238095239,
         "goodput": 10.300796933205595,
         "latency": {
            "mean": 9.3735307242921,
            "std": 2.5982239872051363,
            "m_e": 0.11350389677837591,
            "low": 9.260026827513725,
            "up": 9.487034621070476
         }
      }
   },
   "4": {
      "_info": {
         "end_sent": "2019-12-27 18:57:57.106404",
         "end_test": "2019-12-27 18:58:10.378795",
         "start": "2019-12-27 18:51:39.215269",
         "time_send": "0:6.17 [h:m.s]",
         "time_test": "0:6.31 [h:m.s]"
      },
      "mex_": {
         "S": 2520,
         "R": 1978,
         "L": 542,
         "E": 0
      },
      "statistic_": {
         "sample_size": 1978,
         "pdr": 0.7849206349206349,
         "goodput": 10.113417374195569,
         "latency": {
            "mean": 9.268203532103135,
            "std": 2.6814297612390616,
            "m_e": 0.11817057616853727,
            "low": 9.150032955934597,
            "up": 9.386374108271673
         }
      }
   },
   "5": {
      "_info": {
         "end_sent": "2019-12-27 19:06:04.027228",
         "end_test": "2019-12-27 19:06:17.458733",
         "start": "2019-12-27 18:59:46.178198",
         "time_send": "0:6.17 [h:m.s]",
         "time_test": "0:6.31 [h:m.s]"
      },
      "mex_": {
         "S": 2520,
         "R": 1932,
         "L": 588,
         "E": 0
      },
      "statistic_": {
         "sample_size": 1932,
         "pdr": 0.7666666666666667,
         "goodput": 9.875267626078053,
         "latency": {
            "mean": 9.423217397774328,
            "std": 2.5814177144263306,
            "m_e": 0.1151094016183053,
            "low": 9.308107996156023,
            "up": 9.538326799392634
         }
      }
   },
   "summary": {
      "mex_": {
         "S": 2520.0,
         "R": 1992.0,
         "L": 528.0,
         "E": 0.0
      },
      "statistic_": {
         "pdr": 0.7904761904761906,
         "goodput": 10.185425291712386,
         "latency": {
            "mean": 9.339745680678373,
            "std": 2.619987959332371,
            "m_e": 0.11506458091902745,
            "low": 9.224681099759346,
            "up": 9.4548102615974
         }
      }
   }
}